<?xml version="1.0" encoding="utf-8" ?>
<c:Screen xmlns:c="BitMobile.Controls" xmlns:s="BitMobile.ValueStack" StyleSheet="tasks.css">

<!--	<s:Push Id="main" Value="$workflow.main"></s:Push>-->
	<!--<s:Push Id="Main" Value="$workflow.Main"></s:Push>-->


	<s:Push Id="event" Value="$GetEventDetails($param1)"></s:Push>
	<s:Push Id="exTasks" Value="$GetExecutedTasks($event)"></s:Push>
	<s:Push Id="newTasks" Value="$GetNotExecutedTasks($event)"></s:Push>


	<c:VerticalLayout>





 <c:DockLayout CssClass="top_navigator">
      <c:HorizontalLayout CssClass="btn_back" OnEvent="Back" OnClickAction="$DoBackAndClean()">
         <c:Image/>
        <c:TextView Text="#back#"/>
      </c:HorizontalLayout>
				<c:HorizontalLayout CssClass="btn_forward" OnEvent="Back" OnClickAction="$DoAction(Total, $event)">
				<c:TextView Text="#next#"/>
				</c:HorizontalLayout>
      <c:HorizontalLayout>
        <c:TextView Text="#tasks# " />
      </c:HorizontalLayout>
    </c:DockLayout>

		<c:Image CssClass="2_scroll"></c:Image>
		<c:HorizontalLine />

			<c:ScrollView Id="grScrollView">

			<c:HorizontalLayout CssClass="caption_grid">
				<c:TextView Text="#newTasks#:"></c:TextView>
			</c:HorizontalLayout>
			<c:HorizontalLine />

			<s:Iterator Id="itask" Value="$newTasks">

				<c:SwipeHorizontalLayout Id="swipe_layout1" CssClass="swipe_layout" Index="1">
					<c:HorizontalLayout CssClass="green_swipe" OnClickAction="$CompleteTheTask($itask.Id, $workflow.tasks, $param1)">
						<c:VerticalLayout>
							<c:Image></c:Image>
							<c:TextView Text="#execute#"></c:TextView>
						</c:VerticalLayout>
					</c:HorizontalLayout>
					<c:DockLayout CssClass="grid" OnClickAction="$DoAction(task, $itask.Id, null)">
						<c:Image />
						<c:VerticalLayout>
							<c:TextView Text="$itask.Description" CssClass="description_row"></c:TextView>
							<c:TextView Text="$itask.Terget" CssClass="main_row"></c:TextView>
						</c:VerticalLayout>
					</c:DockLayout>
				</c:SwipeHorizontalLayout>
				<c:HorizontalLine />

			</s:Iterator>



			<c:HorizontalLayout CssClass="end_of_block" />

			<c:HorizontalLayout CssClass="caption_grid">
				<c:TextView Text="#executedtask#:"></c:TextView>
			</c:HorizontalLayout>
			<c:HorizontalLine />

			<s:Iterator Id="eTask" Value="$exTasks">

			<c:SwipeHorizontalLayout Id="swipe_layout2" CssClass="swipe_layout">
					<c:DockLayout CssClass="grid" OnClickAction="$DoAction(task, $eTask.Id, null)">
						<c:VerticalLayout CssClass="$getStatusStyle($eTask.Result)"></c:VerticalLayout>
						<c:Image />
						<c:VerticalLayout>
							<c:TextView Text="$eTask.Description" CssClass="description_row"></c:TextView>
							<c:TextView Text="$eTask.Terget" CssClass="main_row"></c:TextView>
						</c:VerticalLayout>
					</c:DockLayout>
					<c:HorizontalLayout CssClass="gray_swipe" OnClickAction="$RetrieveTask($eTask.Id)">
						<c:VerticalLayout>
							<c:Image></c:Image>
							<c:TextView Text="#retrieve#"></c:TextView>
						</c:VerticalLayout>
					</c:HorizontalLayout>
				</c:SwipeHorizontalLayout>
				<c:HorizontalLine />

			</s:Iterator>




			<c:HorizontalLayout CssClass="end_of_block" />

		</c:ScrollView>

	</c:VerticalLayout>

</c:Screen>
